wallabag2readwise/__init__.py
wallabag2readwise/__main__.py
wallabag2readwise/cli.py
wallabag2readwise/logging.py
wallabag2readwise/misc.py
wallabag2readwise/models.py
wallabag2readwise/output.py
wallabag2readwise/utils.py
wallabag2readwise/wallabag.py
wallabag2readwise-1.5.0.dist-info/LICENSE
wallabag2readwise-1.5.0.dist-info/METADATA
wallabag2readwise-1.5.0.dist-info/WHEEL
wallabag2readwise-1.5.0.dist-info/entry_points.txt
wallabag2readwise-1.5.0.dist-info/top_level.txt
wallabag2readwise-1.5.0.dist-info/RECORD
