Metadata-Version: 2.1
Name: wallabag2readwise
Version: 1.5.0
Summary: Push wallabag annotations to Readwise highlights
Home-page: https://github.com/rwxd/wallabag2readwise
Author: rwxd
Author-email: rwxd@pm.me
License: MIT
Classifier: Programming Language :: Python :: 3.6
Classifier: Programming Language :: Python :: 3.7
Classifier: Programming Language :: Python :: 3.8
License-File: LICENSE
Requires-Dist: readwise (==1.1.0)
Requires-Dist: requests (==2.28.2)
Requires-Dist: rich (==13.3.2)
Requires-Dist: typer (==0.8.0)
